osr2mp4app/CustomPP.py
osr2mp4app/Info.py
osr2mp4app/__init__.py
osr2mp4app/abspath.py
osr2mp4app/config_data.py
osr2mp4app/install.py
osr2mp4app/main.py
osr2mp4app/options_config.json
osr2mp4app/ppoptions_config.json
osr2mp4app/run_osu.py
osr2mp4app/updater.py
osr2mp4app/BaseComponents/Buttons.py
osr2mp4app/BaseComponents/ComboBox.py
osr2mp4app/BaseComponents/PathBox.py
osr2mp4app/BaseComponents/__init__.py
osr2mp4app/HomeComponents/AutoCheckBox.py
osr2mp4app/HomeComponents/LanguageDropDown.py
osr2mp4app/HomeComponents/Logo.py
osr2mp4app/HomeComponents/PathImage.py
osr2mp4app/HomeComponents/PopupWindow.py
osr2mp4app/HomeComponents/ProgressBar.py
osr2mp4app/HomeComponents/SkinDropDown.py
osr2mp4app/HomeComponents/__init__.py
osr2mp4app/HomeComponents/Buttons/CancelButton.py
osr2mp4app/HomeComponents/Buttons/FolderButton.py
osr2mp4app/HomeComponents/Buttons/MapsetButton.py
osr2mp4app/HomeComponents/Buttons/Options.py
osr2mp4app/HomeComponents/Buttons/OsrButton.py
osr2mp4app/HomeComponents/Buttons/OsrGrayButton.py
osr2mp4app/HomeComponents/Buttons/OutputButton.py
osr2mp4app/HomeComponents/Buttons/StartButton.py
osr2mp4app/HomeComponents/Buttons/UpdateButton.py
osr2mp4app/HomeComponents/Buttons/__init__.py
osr2mp4app/HomeComponents/Buttons/osuButton.py
osr2mp4app/HomeComponents/Buttons/osuMapButton.py
osr2mp4app/PPComponents/Buttons.py
osr2mp4app/PPComponents/Layout.py
osr2mp4app/PPComponents/Menu.py
osr2mp4app/PPComponents/__init__.py
osr2mp4app/SettingComponents/__init__.py
osr2mp4app/SettingComponents/Components/Buttons.py
osr2mp4app/SettingComponents/Components/CheckBox.py
osr2mp4app/SettingComponents/Components/DoubleSlider.py
osr2mp4app/SettingComponents/Components/Pathbox.py
osr2mp4app/SettingComponents/Components/QLabel.py
osr2mp4app/SettingComponents/Components/RangeSlider.py
osr2mp4app/SettingComponents/Components/Scrollbar.py
osr2mp4app/SettingComponents/Components/Separator.py
osr2mp4app/SettingComponents/Components/Slider.py
osr2mp4app-0.0.6a1.dist-info/METADATA
osr2mp4app-0.0.6a1.dist-info/WHEEL
osr2mp4app-0.0.6a1.dist-info/top_level.txt
osr2mp4app-0.0.6a1.dist-info/RECORD
