Metadata-Version: 2.1
Name: osr2mp4app
Version: 0.0.6a1
Summary: Gui version of osr2mp4
Home-page: https://github.com/uyitroa/osr2mp4-app
Author: yuitora
Author-email: shintaridesu@gmail.com
License: UNKNOWN
Platform: UNKNOWN
Classifier: Programming Language :: Python :: 3
Classifier: License :: OSI Approved :: MIT License
Classifier: Operating System :: OS Independent
Requires-Python: >=3.6
Requires-Dist: autologging
Requires-Dist: PyQt5
Requires-Dist: psutil
Requires-Dist: configparser
Requires-Dist: osrparse
Requires-Dist: osr2mp4 (>=0.0.5.a2)
